MO_RLMS.py
MO_RLMS-0.0.1.dist-info/LICENSE
MO_RLMS-0.0.1.dist-info/METADATA
MO_RLMS-0.0.1.dist-info/WHEEL
MO_RLMS-0.0.1.dist-info/top_level.txt
MO_RLMS-0.0.1.dist-info/RECORD
